simpleacls/__init__.py
simpleacls/acls.py
simpleacls/apps.py
simpleacls/exceptions.py
simpleacls/testutils.py
django_simple_acl-0.1.0.dist-info/LICENSE
django_simple_acl-0.1.0.dist-info/METADATA
django_simple_acl-0.1.0.dist-info/WHEEL
django_simple_acl-0.1.0.dist-info/top_level.txt
django_simple_acl-0.1.0.dist-info/RECORD
