Metadata-Version: 2.1
Name: django-simple-acl
Version: 0.1.0
Summary: Access control lists tied to django groups
Home-page: https://github.com/MaxLarue/django-simple-acl/
Author: MaxLarue
Author-email: maximilienlarue@gmail.com
License: MIT
Platform: UNKNOWN
Requires-Dist: Django (>=2.7)
